README.txt
setup.py
Products/__init__.py
Products.FoundationMember.egg-info/PKG-INFO
Products.FoundationMember.egg-info/SOURCES.txt
Products.FoundationMember.egg-info/dependency_links.txt
Products.FoundationMember.egg-info/namespace_packages.txt
Products.FoundationMember.egg-info/not-zip-safe
Products.FoundationMember.egg-info/requires.txt
Products.FoundationMember.egg-info/top_level.txt
Products/FoundationMember/__init__.py
Products/FoundationMember/config.py
Products/FoundationMember/configure.zcml
Products/FoundationMember/profiles/default/metadata.xml
Products/FoundationMember/profiles/default/skins.xml
Products/FoundationMember/profiles/default/types.xml
Products/FoundationMember/profiles/default/workflows.xml
Products/FoundationMember/profiles/default/types/FoundationMember.xml
Products/FoundationMember/profiles/default/workflows/foundation_member_workflow/definition.xml
Products/FoundationMember/skins/foundationmember/computeMembers.py
Products/FoundationMember/skins/foundationmember/foundationmember_edit.pt
Products/FoundationMember/skins/foundationmember/foundationmember_view.pt
Products/FoundationMember/skins/foundationmember/status_listing.pt
Products/FoundationMember/types/FoundationMember.py
Products/FoundationMember/types/__init__.py
docs/AUTHORS.txt
docs/HISTORY.txt
docs/INSTALL.txt
docs/LICENSE.GPL
docs/LICENSE.txt