Metadata-Version: 1.0
Name: Products.FoundationMember
Version: 1.2
Summary: Product for Foundation Members.
Home-page: http://svn.plone.org/svn/plone/Products.FoundationMember
Author: Plone Foundation
Author-email: plone-developers@lists.sourceforge.net
License: GPL
Platform: UNKNOWN
Classifier: Framework :: Plone
Classifier: Programming Language :: Python
Classifier: Topic :: Software Development :: Libraries :: Python Modules
